{
  "abstract": "Fault tolerance in quantum protocols requires contributions from error-correcting codes and their suitable decoders. Quantum Low-Density Parity Check (QLDPC) codes are one of the most explored quantum codes that have good coding rate and efficient decoders. Iterative message passing-based decoders, although fast, fail to produce suitable success rates due to the colossal degeneracy and short cycles intrinsic to these codes. In this work we present a strategy to improve the performance of the Belief Propagation (BP) decoding, specifically the min-sum algorithm. We propose a collaborative decoding framework that integrates message passing with stabilizer check node removals. We further introduce the concept of ``qubit separation\" and show that the improved decoding performance is directly related to the generation of highly separated trapped data qubits. To guide a more selective removal of check nodes that constrain the separation of the trapped data qubits, we introduce information measurements (IMs) for the data qubits and their adjacent stabilizer checks. We evaluate the performance of the proposed collaborative decoder on Generalized Hypergraph Product (GHP) codes and demonstrate that appropriate decoder configurations mitigate trapping sets in min-sum decoding without significant overhead.",
  "arxiv_id": "2501.08036",
  "arxiv_version": "v3",
  "authors": [
    "Mainak Bhattacharyya",
    "Ankur Raina"
  ],
  "categories": [
    "quant-ph",
    "cs.IT"
  ],
  "extraction_hash": "d08a77ed2007de5169db62754b7d17a78a169e45f469e073ceb5b8a4a83dbbdf",
  "last_processed_at": "2026-04-27T14:11:57.198442+00:00",
  "links": {
    "abs_url": "https://arxiv.org/abs/2501.08036v3",
    "code_repo_urls": [],
    "doi": null,
    "pdf_url": "https://arxiv.org/pdf/2501.08036v3"
  },
  "primary_category": "quant-ph",
  "source_hash": "b125860b82bd870773e1ed4f29466b2f65a695e355948e9d84281692083745dc",
  "submitted_date": "2025-01-14",
  "tags": [
    "belief propagation",
    "cs.IT",
    "decoder",
    "decoding",
    "hypergraph product",
    "quant-ph",
    "relevance:maybe"
  ],
  "title": "Decoding Quantum LDPC Codes using Collaborative Check Node Removal",
  "updated_date": "2026-04-23"
}
